StructuralCausalModels/__init__.py
StructuralCausalModels/dag.py
StructuralCausalModels/directed_graph.py
StructuralCausalModels/graph.py
StructuralCausalModels/graph_via_adjacency_lists.py
StructuralCausalModels/graph_via_adjacency_matrix.py
StructuralCausalModels/graph_via_edges.py
StructuralCausalModels/linear_structural_causal_model.py
StructuralCausalModels/structural_causal_model.py
StructuralCausalModels/structural_equation.py
StructuralCausalModels/test/__init__.py
StructuralCausalModels/test/test_dag.py
StructuralCausalModels/test/test_directed_graph.py
StructuralCausalModels/test/test_graph.py
StructuralCausalModels/test/test_graph_via_adjacency_lists.py
StructuralCausalModels/test/test_graph_via_adjacency_matrix.py
StructuralCausalModels/test/test_graph_via_edges.py
StructuralCausalModels/test/test_linear_structural_causal_model.py
StructuralCausalModels/test/test_structural_causal_model.py
StructuralCausalModels-3.2.0.dist-info/LICENSE
StructuralCausalModels-3.2.0.dist-info/METADATA
StructuralCausalModels-3.2.0.dist-info/WHEEL
StructuralCausalModels-3.2.0.dist-info/top_level.txt
StructuralCausalModels-3.2.0.dist-info/RECORD
