Metadata-Version: 2.1
Name: StructuralCausalModels
Version: 3.2.0
Summary: A Python package for Structural Causal Models.
Home-page: https://github.com/Black-Swan-ICL/PySCMs
Author: K. M-H
Author-email: kmh.pro@protonmail.com
License: MIT
Platform: UNKNOWN
Classifier: License :: OSI Approved :: MIT License
Classifier: Programming Language :: Python :: 3
Classifier: Programming Language :: Python :: 3.8
Classifier: Topic :: Scientific/Engineering
Classifier: Topic :: Scientific/Engineering :: Information Analysis
Classifier: Intended Audience :: Science/Research
Requires-Dist: numpy
Requires-Dist: scipy
Requires-Dist: pandas
Requires-Dist: pytest
Requires-Dist: pytest-cov
